{
  "recordset": [
  {
    "id": 31945918,
    "DELIVERY_NUMBER":31945918,
    "CUSTOMER_NAME":"NORAUTRON AB",
    "SALES_ORDER":11240811,
    "LINE_NUMBER":"1.1",
    "PART_NUMBER":"1N4148 A0^TAIWANSEMI",
    "QUANTITY":5000,
    "CATALOG_ID":1147539,
    "ORDER_OWNER_NAME":"Heinemann, Johanna",
    "ORDER_OWNER_EMAIL":"Johanna.Heinemann@abc.com",
    "ORDER_OWNER_GID":"A12345",
    "ORDER_CSR_NAME":"Heinemann, Johanna",
    "ORDER_CSR_EMAIL":"Johanna.Heinemann@abc.com",
    "ORDER_CSR_GID":"A12345",
    "ORDER_FSR_NAME":"Johansson, Peter",
    "ORDER_FSR_EMAIL":"Peter.Johansson@abc.com",
    "ORDER_FSR_GID":"A56789",
    "ORDER_ISR_NAME":"Heinemann, Johanna",
    "ORDER_ISR_EMAIL":"Johanna.Heinemann@abc.com",
    "ORDER_ISR_GID":"A12345",
    "SPH_CODE":"1BC",
    "EB":"SE_SE_Kista_Core_Cust_Group_EMS"
  },
  {
    "id": 31961085,
    "DELIVERY_NUMBER":31961085,
    "CUSTOMER_NAME":"Dynamic Precision Solutions AB",
    "SALES_ORDER":11298916,
    "LINE_NUMBER":"1.1",
    "PART_NUMBER":"NFM18PC104R1C3D^MURATA",
    "QUANTITY":4000,
    "CATALOG_ID":1073896,
    "ORDER_OWNER_NAME":"Heinemann, Johanna",
    "ORDER_OWNER_EMAIL":"Johanna.Heinemann@abc.com",
    "ORDER_OWNER_GID":"A12345",
    "ORDER_CSR_NAME":"Heinemann, Johanna",
    "ORDER_CSR_EMAIL":"Johanna.Heinemann@abc.com",
    "ORDER_CSR_GID":"A12345",
    "ORDER_FSR_NAME":"Johansson, Peter",
    "ORDER_FSR_EMAIL":"Peter.Johansson@abc.com",
    "ORDER_FSR_GID":"A56789",
    "ORDER_ISR_NAME":"Heinemann, Johanna",
    "ORDER_ISR_EMAIL":"Johanna.Heinemann@abc.com",
    "ORDER_ISR_GID":"A12345",
    "SPH_CODE":null,
    "EB":"SE_SE_Kista_Core_Cust_Group_EMS"
  },
  {
    "id": 31991475,
    "DELIVERY_NUMBER":31991475,
    "CUSTOMER_NAME":"NORAUTRON AB",
    "SALES_ORDER":11297173,
    "LINE_NUMBER":"4.1",
    "PART_NUMBER":"SFH 4646^OSRAMOPTO",
    "QUANTITY":10000,
    "CATALOG_ID":1332741,
    "ORDER_OWNER_NAME":"Heinemann, Johanna",
    "ORDER_OWNER_EMAIL":"Johanna.Heinemann@abc.com",
    "ORDER_OWNER_GID":"A12345",
    "ORDER_CSR_NAME":"Heinemann, Johanna",
    "ORDER_CSR_EMAIL":"Johanna.Heinemann@abc.com",
    "ORDER_CSR_GID":"A12345",
    "ORDER_FSR_NAME":"Johansson, Peter",
    "ORDER_FSR_EMAIL":"Peter.Johansson@abc.com",
    "ORDER_FSR_GID":"A56789",
    "ORDER_ISR_NAME":"Heinemann, Johanna",
    "ORDER_ISR_EMAIL":"Johanna.Heinemann@abc.com",
    "ORDER_ISR_GID":"A12345",
    "SPH_CODE":"1BC",
    "EB":"SE_SE_Kista_Core_Cust_Group_EMS"
  },
  {
    "id": 30608696,
    "DELIVERY_NUMBER":30608696,
    "CUSTOMER_NAME":"Dynamic Precision Solutions AB",
    "SALES_ORDER":11201959,
    "LINE_NUMBER":"14.1",
    "PART_NUMBER":"BTS50081EKBXUMA1^INFINEON",
    "QUANTITY":5000,
    "CATALOG_ID":5915631,
    "ORDER_OWNER_NAME":"Heinemann, Johanna",
    "ORDER_OWNER_EMAIL":"Johanna.Heinemann@abc.com",
    "ORDER_OWNER_GID":"A12345",
    "ORDER_CSR_NAME":"Heinemann, Johanna",
    "ORDER_CSR_EMAIL":"Johanna.Heinemann@abc.com",
    "ORDER_CSR_GID":"A12345",
    "ORDER_FSR_NAME":"Johansson, Peter",
    "ORDER_FSR_EMAIL":"Peter.Johansson@abc.com",
    "ORDER_FSR_GID":"A56789",
    "ORDER_ISR_NAME":"Heinemann, Johanna",
    "ORDER_ISR_EMAIL":"Johanna.Heinemann@abc.com",
    "ORDER_ISR_GID":"A12345",
    "SPH_CODE":null,
    "EB":"SE_SE_Kista_Core_Cust_Group_EMS"
  }
  ]
}
